{
  "id": "0xcc2bd8cbba68f1fe46e89445b61e2c581ea96527438889eb749a852fba647920_2025-12-07",
  "source": "polymarket",
  "question": "Epstein or Maxwell confirmed Mossad operatives in 2025?",
  "resolution_criteria": "This market will resolve to \"Yes\" if previously unreleased evidence definitively confirming that either Jeffrey Epstein or Ghislaine Maxwell were Mossad operatives is made public by December 31 2025, 11:59 PM ET. Otherwise, this market will resolve to \"No\".\n\nFor the purpose of this market \u2018operative\u2019 includes any direct involvement in assisting or providing information to Mossad.\n\nOfficial confirmation from the Trump administration or the Israeli government will qualify as definitive evidence.  \n\nThe resolution source for this market will be a consensus of credible reporting. ",
  "background": "",
  "url": "https://polymarket.com/market/epstein-or-maxwell-confirmed-mossad-opperatives-in-2025",
  "forecast_due_date": "2025-12-07",
  "resolved_to": 0.0,
  "resolution_date": "2025-12-31",
  "market_value": "0.048",
  "market_date": "2025-11-27",
  "market_value_explanation": "The market price."
}