{
  "id": "NHOdIsbno3EUF8fXm3vx_2026-04-26",
  "source": "manifold",
  "question": "Can we give a birth to human from artificial womb in this decade?",
  "resolution_criteria": "Can we be able to develop such technologies till 2030? ",
  "background": "",
  "url": "https://manifold.markets/fullerov/can-we-give-a-birth-to-human-from-a",
  "resolution_dates": "N/A",
  "forecast_due_date": "2026-04-26",
  "resolved_to": null,
  "market_value": "0.19485068527784602",
  "market_date": "2026-04-16",
  "market_value_explanation": "The market value."
}