{
  "id": "Wjp8k8ixLykVvyZ5iFeT_2026-04-12",
  "source": "manifold",
  "question": "Is the One Piece Treasure actually Binks' Sake?",
  "resolution_criteria": "There is a old pirate song which regularly reappears in One Piece, known as Binks' Sake.\n\nGather up all of the crew, it's time to ship out Binks' brew.\nSea wind blows, to where, who knows? The waves will be our guide.\nO'er across the ocean's tide. Rays of sunshine far and wide.\nBirds they sing, of cheerful things, in circles passing by.\n\nThe song has strong ties to the overall themes of One Piece, and a well-known and much upvoted fan theory is that the mysterious One Piece Treasure is in fact somehow the very Sake that the song is about. \n\nLikely it is not just mundane sake, but some sort of magical liquid, bottle, etc. It could perhaps turn out to be something like the Fountain of Youth, or a giant golden sake cup, or a devil fruit that can create infinite sake. Any of these would count, as long as there is some clear tie from Binks' Sake to the One Piece Treasure. It also counts if there are multiple parts of the One Piece treasure, and only part of it is Binks' Sake. \n\nOda could do a lot of weird things here, and this is about the spirit of the theory and not the letter.\n\nThis market remains open until the full nature of the One Piece is known. If the theory is validated, this market resolves YES. Otherwise, it resolves NO.\n\nI will not trade on this question, so as to keep myself unbiased.\n\nGather up all of the crew, it\u2019s time to ship out Binks\u2019 brew.\nSing a song, and play along for all the oceans wide.\nAfter all is said and done, you'll end up a skeleton,\nso spread your tale from dawn 'til dusk upon these foamy seas.",
  "background": "",
  "url": "https://manifold.markets/Joshua/does-the-one-piece-treasure-binks-s",
  "resolution_dates": "N/A",
  "forecast_due_date": "2026-04-12",
  "resolved_to": null,
  "market_value": "0.264469754887789",
  "market_date": "2026-04-02",
  "market_value_explanation": "The market value."
}