{"organization":"sirbayes","model":"pro-high-brave-c0-t0_calibrated_global","model_organization":"sirbayes","forecast_due_date":"2025-04-29","question_set":"","leaderboard_eligible":true,"config":{},"forecasts":[{"id":"aibq2_0011","source":"aibq2","resolution_date":"2025-06-01","forecast":0.22565183261899213,"raw_trials":[0.22565183261899213],"resolved_to":0.0,"forecast_due_date":"2025-04-29","market_value":"","market_date":"","reasoning":"The ruling party (RHDP) has consistently pushed for Alassane Ouattara to run for a fourth term, declaring him their 'natural candidate'. Ouattara himself hinted in January 2025 that he was open to running, stating he is in good health and eager to serve. In March 2025, party leadership confirmed that he would 'soon be invested' as their candidate. Crucially, the RHDP has scheduled an ordinary congress for May 17 and 18, 2025, where the official nomination and his acceptance are expected to take place. An acceptance speech at this meticulously planned convention comfortably fulfills the criteria of declaring his candidacy before the June 1, 2025 deadline. The main risks are a sudden health issue, an unexpected last-minute choice of a successor, or a minor delay in the congress date pushing the declaration to June. However, with the congress recently scheduled for mid-May and the party unified behind him, the likelihood of a declaration prior to June 1 is very high.","n_steps":48,"submitted":true,"tokens_in":506094,"tokens_out":31666,"elapsed_seconds":719.5,"imputed":false,"tool_counts":{"web_search":6,"summarize_results":1,"submit":1},"n_searches":6}]}