{"organization":"sirbayes","model":"kimi-k2t-high-brave-c0-t0_calibrated_global","model_organization":"sirbayes","forecast_due_date":"2025-04-22","question_set":"","leaderboard_eligible":true,"config":{},"forecasts":[{"id":"aibq2_0003","source":"aibq2","resolution_date":"2025-05-05","forecast":0.11547504480200751,"raw_trials":[0.11547504480200751],"resolved_to":1.0,"forecast_due_date":"2025-04-22","market_value":"","market_date":"","reasoning":"Agent submitted with p=0.350. Evidence for: []. Evidence against: [].","n_steps":48,"submitted":true,"tokens_in":330659,"tokens_out":19748,"elapsed_seconds":1746.4,"imputed":false,"tool_counts":{"web_search":6,"summarize_results":3,"submit":1},"n_searches":6}],"forecasts_aggregated":{"mean:1":[0.11547504480200751],"mean:3":[0.11547504480200751],"mean:5":[0.11547504480200751],"logit-mean:5":[0.11547504480200751],"shrink-std:5":[0.11547504480200751],"shrink-fit:5":[0.11547504480200751],"median:5":[0.11547504480200751]}}