{
  "id": "31071_2026-04-12",
  "source": "metaculus",
  "question": "Will Israel be found guilty in South Africa's genocide case by the ICJ before 2027?",
  "resolution_criteria": "This question will resolve as **Yes** if, before January 1, 2027, the International Court of Justice finds that Israel has violated international law in South Africa's genocide case. If this does not happen before January 1, 2027, this question will resolve as **No**.",
  "background": "*This forecasting question is associated with the Verity controversy:* Will Israel be found guilty in South Africa's genocide case before the International Court of Justice?\n\nThis forecasting question pertains to the [<u>ongoing legal proceedings initiated by South Africa against Israel at the International Court of Justice (ICJ)</u>](https://www.icj-cij.org/case/192). The case alleges that Israel has committed acts of genocide against the Palestinian population, invoking the [<u>1948 Convention on the Prevention and Punishment of the Crime of Genocide</u>](https://www.un.org/en/genocideprevention/documents/atrocity-crimes/Doc.1_Convention%20on%20the%20Prevention%20and%20Punishment%20of%20the%20Crime%20of%20Genocide.pdf), to which both [<u>countries are signatories</u>](https://treaties.un.org/pages/ViewDetails.aspx?src=TREATY\\&mtdsg_no=IV-1\\&chapter=4).\n\nThe case, filed in [<u>December 2023</u>](https://www.icj-cij.org/sites/default/files/case-related/192/192-20231229-pre-01-00-en.pdf), emerges amidst heightened tensions following the Israel-Gaza [<u>war</u>](https://en.wikipedia.org/wiki/Israel%E2%80%93Hamas_war#:~:text=An%20armed%20conflict%20between%20Israel,Yom%20Kippur%20War%20in%201973.), which have intensified global scrutiny of Israel's policies in the occupied territories. South Africa\u2019s government, historically vocal in its support for Palestinian self-determination, argues that Israel\u2019s actions meet the legal criteria for genocide as defined in Article II of the Genocide Convention. Along with South Africa, at least [<u>14 other countries</u>](https://unric.org/en/south-africa-vs-israel-14-other-countries-intend-to-join-the-icj-case/) have joined the suit.\n\nIsrael has strongly denied the allegations, calling them \u201c[<u>baseless</u>](https://www.jpost.com/international/article-781745)\u201d and politically motivated. Its representatives argue that the measures taken in the West Bank and Gaza Strip are consistent with its [<u>right to </u>](https://legal.un.org/repertory/art51/english/rep_supp3_vol2_art51.pdf)<u>self-defence</u> and do not meet the legal threshold for genocide. For its part, the ICJ is tasked with [<u>determining whether the case has merit</u>](https://www.icj-cij.org/sites/default/files/case-related/192/192-20240126-sum-01-00-en.pdf) and, ultimately, whether Israel\u2019s actions constitute a violation of international law.\n\nThe resolution of this question is uncertain, given the legal, political, and evidentiary complexities involved. The ICJ\u2019s verdict is expected to depend on a combination of the submitted evidence, legal arguments, and the broader context of international law enforcement.",
  "url": "https://www.metaculus.com/questions/31071",
  "resolution_dates": "N/A",
  "forecast_due_date": "2026-04-12",
  "resolved_to": null,
  "market_value": "0.25",
  "market_date": "2026-04-02",
  "market_value_explanation": "The community prediction."
}